vci/__init__.py
vci/__version__.py
vci/argument_parsing.py
vci/common.py
vci/config.py
vci/console.py
vci/find.py
vci/index_contents.py
vci-0.2.8.dist-info/LICENSE
vci-0.2.8.dist-info/METADATA
vci-0.2.8.dist-info/WHEEL
vci-0.2.8.dist-info/entry_points.txt
vci-0.2.8.dist-info/top_level.txt
vci-0.2.8.dist-info/RECORD
