Metadata-Version: 2.1
Name: vci
Version: 0.2.8
Summary: version control management from an index of listed workspaces
Home-page: http://github.com/stonier/vci
Author: Daniel Stonier
Author-email: d.stonier@gmail.com
Maintainer: Daniel Stonier
Maintainer-email: d.stonier@gmail.com
License: BSD
Keywords: vcs
Platform: UNKNOWN
Classifier: Environment :: Console
Classifier: Intended Audience :: Developers
Classifier: License :: OSI Approved :: BSD License
Classifier: Programming Language :: Python
Classifier: Topic :: Software Development :: Version Control
Classifier: Topic :: Utilities
Requires-Dist: distro
Requires-Dist: pyyaml
Provides-Extra: packaging
Requires-Dist: stdeb ; extra == 'packaging'
Requires-Dist: twine ; extra == 'packaging'
